d2vs/__init__.py
d2vs/constants.py
d2vs/ocr.py
d2vs/ocr_helpers.py
d2vs/pickit.py
d2vs/state_checks.py
d2vs/ocr_model/d2rg.pth
d2vs/ocr_network/d2rg.py
d2vs/ocr_network/d2rg.yaml
d2vs/ocr_network/__pycache__/d2rg.cpython-38.pyc
d2vs-0.0.3.dist-info/LICENSE.txt
d2vs-0.0.3.dist-info/METADATA
d2vs-0.0.3.dist-info/WHEEL
d2vs-0.0.3.dist-info/top_level.txt
d2vs-0.0.3.dist-info/RECORD
