Metadata-Version: 2.1
Name: d2vs
Version: 0.0.3
Summary: Save contacts from your terminal
Home-page: https://github.com/wangonya/contacts-cli
Author: Eric Carmichael
Author-email: eric@ckcollab.com
License: MIT
Platform: UNKNOWN
Classifier: License :: OSI Approved :: MIT License
Classifier: Programming Language :: Python :: 3
Classifier: Programming Language :: Python :: 3.8
License-File: LICENSE.txt
Requires-Dist: easyocr (==1.4.1)
Requires-Dist: numpy (==1.21.4)
